mmd5sum.py
mmd5sum-1.0.0.dist-info/METADATA
mmd5sum-1.0.0.dist-info/WHEEL
mmd5sum-1.0.0.dist-info/entry_points.txt
mmd5sum-1.0.0.dist-info/top_level.txt
mmd5sum-1.0.0.dist-info/RECORD
