Metadata-Version: 2.1
Name: mmd5sum
Version: 1.0.0
Summary: calculate multiple MD5s using multiple processes.
Home-page: https://github.com/soultoolman/mmd5sum
Author: soultoolman
Author-email: soultooman@gmail.com
License: MIT
Platform: UNKNOWN
Classifier: License :: OSI Approved :: MIT License
Classifier: Programming Language :: Python
Classifier: Programming Language :: Python :: 3
Classifier: Programming Language :: Python :: 3.6
Classifier: Programming Language :: Python :: Implementation :: CPython
Classifier: Programming Language :: Python :: Implementation :: PyPy
Requires-Python: >=3.6.0
Requires-Dist: click
Requires-Dist: scandir
